coviolations_app
