Metadata-Version: 1.1
Name: coviolations-app
Version: 0.18
Summary: coviolations.io app
Home-page: http://coviolations.io
Author: Vladimir Iakovlev
Author-email: nvbn.rm@gmail.com
License: MIT
Platform: UNKNOWN
Classifier: Programming Language :: Python :: 2.7
Classifier: Programming Language :: Python :: 3.3
